mindsponge/__init__.py
mindsponge/md/__init__.py
mindsponge/md/npt.py
mindsponge/md/simulation.py
mindsponge/md/control/__init__.py
mindsponge/md/control/bd_baro.py
mindsponge/md/control/crd_molecular_map.py
mindsponge/md/control/langevin_liujian_md.py
mindsponge/md/control/mc_baro.py
mindsponge/md/cybertron/__init__.py
mindsponge/md/cybertron/activations.py
mindsponge/md/cybertron/aggregators.py
mindsponge/md/cybertron/base.py
mindsponge/md/cybertron/blocks.py
mindsponge/md/cybertron/cutoff.py
mindsponge/md/cybertron/cybertron.py
mindsponge/md/cybertron/decoders.py
mindsponge/md/cybertron/interactions.py
mindsponge/md/cybertron/mdnn.py
mindsponge/md/cybertron/meta_dynamics.py
mindsponge/md/cybertron/models.py
mindsponge/md/cybertron/neighbors.py
mindsponge/md/cybertron/rbf.py
mindsponge/md/cybertron/readouts.py
mindsponge/md/cybertron/train.py
mindsponge/md/cybertron/units.py
mindsponge/md/functions/__init__.py
mindsponge/md/functions/angle_energy.py
mindsponge/md/functions/angle_force_with_atom_energy.py
mindsponge/md/functions/bond_energy.py
mindsponge/md/functions/bond_force_with_atom_energy.py
mindsponge/md/functions/common.py
mindsponge/md/functions/crd_to_uint_crd.py
mindsponge/md/functions/dihedral_14_cf_energy.py
mindsponge/md/functions/dihedral_14_lj_energy.py
mindsponge/md/functions/dihedral_14_ljcf_force_with_atom_energy.py
mindsponge/md/functions/dihedral_energy.py
mindsponge/md/functions/dihedral_force_with_atom_energy.py
mindsponge/md/functions/lj_energy.py
mindsponge/md/functions/lj_force_pme_direct_force.py
mindsponge/md/functions/md_iteration_leap_frog_liujian.py
mindsponge/md/functions/md_temperature.py
mindsponge/md/functions/neighbor_list_update.py
mindsponge/md/functions/pme_common.py
mindsponge/md/functions/pme_energy.py
mindsponge/md/functions/pme_excluded_force.py
mindsponge/md/functions/pme_reciprocal_force.py
mindsponge/md/partition/__init__.py
mindsponge/md/partition/neighbor_list.py
mindsponge/md/potential/__init__.py
mindscience_mindsponge_gpu-0.1.0.dist-info/LICENSE
mindscience_mindsponge_gpu-0.1.0.dist-info/METADATA
mindscience_mindsponge_gpu-0.1.0.dist-info/NOTICE
mindscience_mindsponge_gpu-0.1.0.dist-info/WHEEL
mindscience_mindsponge_gpu-0.1.0.dist-info/top_level.txt
mindscience_mindsponge_gpu-0.1.0.dist-info/RECORD
