Metadata-Version: 2.1
Name: mindscience-mindsponge-gpu
Version: 0.1.0
Summary: simulation package of next generation molecular modeling in mindspore
Home-page: https://www.mindspore.cn/
Author: The MindSpore Authors
Author-email: contact@mindspore.cn
License: Apache 2.0
Download-URL: https://gitee.com/mindspore/mindscience/tags
Project-URL: Sources, https://gitee.com/mindspore/mindscience
Project-URL: Issue Tracker, https://gitee.com/mindspore/mindscience/issues
Platform: UNKNOWN
Classifier: License :: OSI Approved :: Apache Software License
Requires-Dist: numpy (>=1.17.0)
